gnfish/align_sequences.py
gnfish/alignment_trimming.py
gnfish/blast.py
gnfish/decompress_genomes.py
gnfish/get_combined_seqs.py
gnfish/get_genomes.py
gnfish/get_query_sequences.py
gnfish/get_raw_sequences.py
gnfish/get_unique_hits.py
gnfish/phylogenetic_inference.py
gnfish/translate_sequences.py
gnfish/utils.py
gnfish-0.1.0.dist-info/LICENSE
gnfish-0.1.0.dist-info/METADATA
gnfish-0.1.0.dist-info/WHEEL
gnfish-0.1.0.dist-info/entry_points.txt
gnfish-0.1.0.dist-info/RECORD
